setup.cfg
setup.py
xyz_distro_distributions/Binomialdistribution.py
xyz_distro_distributions/Gaussiandistribution.py
xyz_distro_distributions/Generaldistribution.py
xyz_distro_distributions/__init__.py
xyz_distro_distributions.egg-info/PKG-INFO
xyz_distro_distributions.egg-info/SOURCES.txt
xyz_distro_distributions.egg-info/dependency_links.txt
xyz_distro_distributions.egg-info/not-zip-safe
xyz_distro_distributions.egg-info/top_level.txt