Metadata-Version: 1.0
Name: xyz-distro-distributions
Version: 0.1
Summary: Gaussian distributions
Home-page: UNKNOWN
Author: UNKNOWN
Author-email: UNKNOWN
License: UNKNOWN
Keywords: one,two
Platform: UNKNOWN
